qwq_tag-0.1.2.dist-info/METADATA
qwq_tag-0.1.2.dist-info/WHEEL
qwq_tag-0.1.2.dist-info/entry_points.txt
qwq_tag/__init__.py
qwq_tag/qwq_tag.py
qwq_tag-0.1.2.dist-info/RECORD
