Metadata-Version: 2.1
Name: qwq-tag
Version: 0.1.2
Summary: QwQ Tag for parsing xml
Author-Email: yanli <mail@yanli.one>
License: MIT
Requires-Python: >=3.10
Requires-Dist: lxml>=6.0.0
Requires-Dist: pydantic>=2.11.7
